{"scenes": [{"objects": [{"prefab_path": "MensCollection/Prefabs/Rearranged/shirt_hung_up28", "unique_id": 0, "index": 0, "bbox": [1, 161, 221, 33], "position": [3.6308958530426025, 2.4008827209472656, 2.3084213733673096]}, {"prefab_path": "WomensCollection/Prefabs/Rearranged/blouse_01_62", "unique_id": 1, "index": 1, "bbox": [19, 145, 210, 95], "position": [4.313000202178955, 2.3940000534057617, 2.312999963760376]}, {"prefab_path": "MensCollection/Prefabs/Rearranged/jacket_1", "unique_id": 2, "index": 2, "bbox": [1121, 202, 190, 75], "position": [3.8602535724639893, -0.519101619720459, -3.4550414085388184]}, {"prefab_path": "WomensCollection/Prefabs/Rearranged/blouse_01_16", "unique_id": 3, "index": 3, "bbox": [1005, 258, 112, 46], "position": [5.038000106811523, 2.367000102996826, -2.220846176147461]}, {"prefab_path": "WomensCollection/Prefabs/Rearranged/dress_shirt_1-1", "unique_id": 4, "index": 4, "bbox": [1055, 236, 141, 56], "position": [4.384999752044678, 2.387723445892334, -2.2210428714752197]}, {"prefab_path": "1498649_store/Prefabs/_itog045", "unique_id": 5, "index": 5, "bbox": [1658, 250, 331, 226], "position": [1.1017653942108154, 1.8418114185333252, -2.220693349838257]}, {"prefab_path": "WomensCollection/Prefabs/Rearranged/blouse_2_1", "unique_id": 6, "index": 6, "bbox": [58, 381, 222, 84], "position": [4.292070388793945, 1.538620948791504, 2.3050241470336914]}, {"prefab_path": "WomensCollection/Prefabs/Rearranged/dress_4_", "unique_id": 7, "index": 7, "bbox": [1012, 384, 175, 35], "position": [4.983198642730713, 1.337825894355774, -2.2572858333587646]}, {"prefab_path": "WomensCollection/Prefabs/Rearranged/dress_3_", "unique_id": 8, "index": 8, "bbox": [1065, 390, 178, 46], "position": [4.349457263946533, 1.3369150161743164, -2.246000051498413]}, {"prefab_path": "WomensCollection/Prefabs/Rearranged/hanging_dress_1_26", "unique_id": 9, "index": 9, "bbox": [1126, 396, 185, 57], "position": [3.7367184162139893, 1.4919672012329102, -2.330535888671875]}, {"prefab_path": "WomensCollection/Prefabs/Rearranged/dress_4_04", "unique_id": 10, "index": 10, "bbox": [800, 531, 37, 58], "position": [3.071714162826538, 0.79982590675354, -0.12919890880584717]}, {"prefab_path": "WomensCollection/Prefabs/Rearranged/dress_4_08", "unique_id": 11, "index": 11, "bbox": [782, 545, 36, 30], "position": [3.320714235305786, 0.7068259716033936, -0.12919890880584717]}, {"prefab_path": "WomensCollection/Prefabs/Rearranged/dress_4_", "unique_id": 7, "index": 12, "bbox": [788, 535, 48, 72], "position": [2.5152857303619385, 0.8938260078430176, 0.10619890689849854]}, {"prefab_path": "MensCollection/Prefabs/Rearranged/sweater_folded29", "unique_id": 12, "index": 13, "bbox": [185, 659, 31, 109], "position": [4.336914539337158, 0.8036502003669739, 1.9639487266540527]}, {"prefab_path": "WomensCollection/Prefabs/Rearranged/sweater_folded_2", "unique_id": 13, "index": 14, "bbox": [325, 641, 35, 102], "position": [4.336914539337158, 0.8041285276412964, 1.4899486303329468]}, {"prefab_path": "MensCollection/Prefabs/Rearranged/shirt_2", "unique_id": 14, "index": 15, "bbox": [319, 668, 26, 98], "position": [4.0377516746521, 0.7826411724090576, 1.4949250221252441]}, {"prefab_path": "WomensCollection/Prefabs/Rearranged/dress_4_", "unique_id": 7, "index": 16, "bbox": [887, 496, 345, 39], "position": [2.646225929260254, 0.9798259735107422, -0.2110658884048462]}, {"prefab_path": "WomensCollection/Prefabs/Rearranged/dress_4_00", "unique_id": 15, "index": 17, "bbox": [928, 527, 311, 45], "position": [2.6900634765625, 0.9020570516586304, -0.4299667477607727]}, {"prefab_path": "MensCollection/Prefabs/Rearranged/shirt_5", "unique_id": 16, "index": 18, "bbox": [128, 709, 37, 128], "position": [3.740993022918701, 0.7826411724090576, 1.975780963897705]}, {"prefab_path": "MensCollection/Prefabs/Rearranged/sweater_folded47", "unique_id": 17, "index": 19, "bbox": [156, 681, 42, 122], "position": [4.037914752960205, 0.8036502003669739, 1.9679487943649292]}, {"prefab_path": "MensCollection/Prefabs/Rearranged/sweater_folded17", "unique_id": 18, "index": 20, "bbox": [302, 684, 43, 108], "position": [3.7499144077301025, 0.8066529035568237, 1.4969487190246582]}, {"prefab_path": "MensCollection/Prefabs/Rearranged/folded polo shirt13", "unique_id": 19, "index": 21, "bbox": [293, 705, 48, 123], "position": [3.4380886554718018, 0.8034321069717407, 1.359958291053772]}, {"prefab_path": "WomensCollection/Prefabs/Rearranged/dress_4_24", "unique_id": 20, "index": 22, "bbox": [655, 573, 341, 47], "position": [2.8764572143554688, 0.7740169167518616, 0.5055165886878967]}, {"prefab_path": "WomensCollection/Prefabs/Rearranged/dress_4_", "unique_id": 7, "index": 23, "bbox": [704, 544, 363, 41], "position": [2.861198902130127, 0.8288259506225586, 0.34671416878700256]}, {"prefab_path": "WomensCollection/Prefabs/Rearranged/dress_6_05", "unique_id": 21, "index": 24, "bbox": [742, 545, 310, 42], "position": [2.8475797176361084, 0.8689459562301636, 0.2079998105764389]}, {"prefab_path": "WomensCollection/Prefabs/Rearranged/dress_3_", "unique_id": 8, "index": 25, "bbox": [766, 568, 357, 143], "position": [2.377000093460083, 0.8479151129722595, 0.10345727205276489]}, {"prefab_path": "MensCollection/Prefabs/Rearranged/folded polo shirt21", "unique_id": 22, "index": 26, "bbox": [84, 734, 47, 152], "position": [3.446542978286743, 0.8034321069717407, 2.0908565521240234]}, {"prefab_path": "MensCollection/Prefabs/Rearranged/sweater_folded47", "unique_id": 17, "index": 27, "bbox": [268, 740, 55, 134], "position": [3.1435132026672363, 0.8041285276412964, 1.4774458408355713]}, {"prefab_path": "WomensCollection/Prefabs/Rearranged/dress2_16", "unique_id": 23, "index": 28, "bbox": [782, 588, 388, 148], "position": [2.2179954051971436, 0.7732959389686584, 0.10299992561340332]}, {"prefab_path": "WomensCollection/Prefabs/Rearranged/sweater_folded09", "unique_id": 24, "index": 29, "bbox": [30, 762, 81, 185], "position": [3.144883632659912, 0.8045907020568848, 1.9727058410644531]}, {"prefab_path": "MensCollection/Prefabs/Rearranged/sweater_folded20", "unique_id": 25, "index": 30, "bbox": [248, 775, 72, 148], "position": [2.8453385829925537, 0.8066529035568237, 1.4658385515213013]}, {"prefab_path": "1514019/Rearranged/Sport_Pants", "unique_id": 26, "index": 31, "bbox": [1627, 636, 348, 186], "position": [1.124466061592102, 0.2701929807662964, -2.179849147796631]}, {"prefab_path": "WomensCollection/Prefabs/Rearranged/shirt_5_03", "unique_id": 27, "index": 32, "bbox": [1, 819, 76, 183], "position": [2.846973419189453, 0.7826354503631592, 1.964170217514038]}], "relationships": {"right": {"0": [5, 16, 12], "1": [5, 16, 17], "6": [16, 17, 10], "10": [17, 31, 5], "11": [31, 5], "12": [31, 5], "13": [15, 11, 10], "14": [11, 10, 17], "15": [11, 10, 17], "16": [31, 5], "17": [31, 5], "18": [21, 23, 24], "19": [20, 10, 17], "20": [17, 10, 24], "21": [23, 24, 22], "22": [23, 24, 12], "23": [24, 16, 12], "24": [16, 17, 31], "25": [31, 5], "26": [27, 25, 12], "27": [25, 12, 28], "28": [31, 5], "29": [30, 28, 25], "30": [28, 25, 12], "32": [30, 28, 25]}, "down": {"0": [26, 29, 18], "1": [6, 19, 13], "3": [7, 8, 2], "4": [8, 9, 2], "5": [31], "6": [13, 19, 18], "8": [2], "9": [2]}, "left": {"2": [14, 13, 15], "3": [1], "4": [1, 6, 14], "5": [0, 6, 12], "7": [13, 6], "8": [14, 13, 15], "9": [14, 13, 6], "10": [19, 15, 20], "11": [13, 15, 14], "12": [27, 26, 22], "14": [13], "15": [13, 19], "16": [24, 23, 21], "17": [20, 19, 24], "20": [19, 18, 13], "21": [18, 19, 26], "22": [18, 21, 27], "23": [21, 18, 22], "24": [23, 21, 18], "25": [26, 27, 29], "27": [26, 29, 18], "28": [29, 30, 26], "30": [29, 32, 26], "31": [28, 29, 26]}, "up": {"32": [0], "2": [9, 8, 4], "6": [1], "7": [3], "8": [4, 3], "9": [4], "13": [6, 1, 0], "14": [1], "15": [1, 0], "18": [0, 1, 6], "19": [6, 1, 0], "20": [0, 1], "21": [0], "26": [0, 1], "27": [0], "29": [0, 1], "30": [0], "31": [5]}}}]}