{"scenes": [{"objects": [{"prefab_path": "MensCollection/Prefabs/Rearranged/long_coat_06", "unique_id": 0, "index": 0, "bbox": [1, 297, 242, 105], "position": [-3.6660923957824707, 0.6689841747283936, 3.1500697135925293]}, {"prefab_path": "870230/hoodie03", "unique_id": 1, "index": 1, "bbox": [47, 319, 201, 48], "position": [-4.20974588394165, 2.0649633407592773, 2.249152183532715]}, {"prefab_path": "1498649_store/Prefabs/_itog040", "unique_id": 2, "index": 2, "bbox": [113, 310, 221, 93], "position": [-3.9216935634613037, 1.8418116569519043, 2.237234592437744]}, {"prefab_path": "1498649_store/Prefabs/_itog040", "unique_id": 2, "index": 3, "bbox": [137, 311, 221, 71], "position": [-3.8096935749053955, 1.8418114185333252, 2.241234540939331]}, {"prefab_path": "MensCollection/Prefabs/Rearranged/long_coat_12", "unique_id": 3, "index": 4, "bbox": [195, 312, 234, 75], "position": [-3.08221697807312, 0.4726707935333252, 1.4224014282226562]}, {"prefab_path": "1498649_store/Prefabs/_itog031", "unique_id": 4, "index": 5, "bbox": [760, 296, 245, 141], "position": [-1.1037654876708984, 1.8418116569519043, 2.2406933307647705]}, {"prefab_path": "MensCollection/Prefabs/Rearranged/jacket_2_03", "unique_id": 5, "index": 6, "bbox": [941, 280, 280, 49], "position": [-2.034717559814453, -1.304472804069519, 0.1491851806640625]}, {"prefab_path": "WomensCollection/Prefabs/Rearranged/leather_jacket_1", "unique_id": 6, "index": 7, "bbox": [1025, 309, 233, 36], "position": [-0.32967859506607056, 1.8607878684997559, 2.248088836669922]}, {"prefab_path": "MensCollection/Prefabs/Rearranged/shirt_hung_up03", "unique_id": 7, "index": 8, "bbox": [985, 294, 263, 41], "position": [-0.45010003447532654, 1.848331093788147, 2.2369842529296875]}, {"prefab_path": "MensCollection/Prefabs/Rearranged/jacket_4_09", "unique_id": 8, "index": 9, "bbox": [1058, 273, 309, 44], "position": [-0.2118884027004242, 1.8144785165786743, 2.2623918056488037]}, {"prefab_path": "MensCollection/Prefabs/Rearranged/jacket_1", "unique_id": 9, "index": 10, "bbox": [1248, 268, 322, 45], "position": [-0.8098739385604858, -1.044653296470642, 2.1298351287841797]}, {"prefab_path": "MensCollection/Prefabs/Rearranged/jacket_3_02", "unique_id": 10, "index": 11, "bbox": [1291, 269, 322, 81], "position": [-1.443185806274414, -2.788418769836426, -3.1178269386291504]}, {"prefab_path": "WomensCollection/Prefabs/Rearranged/blouse_2_15", "unique_id": 11, "index": 12, "bbox": [1423, 296, 256, 167], "position": [1.0958402156829834, 1.8430695533752441, 2.2492973804473877]}, {"prefab_path": "1514019/Rearranged/Sport_Pants", "unique_id": 12, "index": 13, "bbox": [74, 569, 218, 73], "position": [-4.3703837394714355, 0.2701929807662964, 2.2160725593566895]}, {"prefab_path": "1514019/Rearranged/Jeans_Blue", "unique_id": 13, "index": 14, "bbox": [208, 570, 239, 91], "position": [-3.613121509552002, 0.24459731578826904, 2.2062573432922363]}, {"prefab_path": "1514019/Rearranged/Sport_Pants", "unique_id": 12, "index": 15, "bbox": [360, 583, 238, 94], "position": [-2.8943309783935547, 0.2701929807662964, 2.1931071281433105]}, {"prefab_path": "clothing_store/models/prefab/trousers", "unique_id": 14, "index": 16, "bbox": [762, 588, 272, 139], "position": [-1.1222920417785645, 0.2301410436630249, 2.24706768989563]}, {"prefab_path": "clothing_store/models/prefab/trousers_3", "unique_id": 15, "index": 17, "bbox": [957, 600, 290, 152], "position": [-0.34700000286102295, 0.23014092445373535, 2.201373815536499]}, {"prefab_path": "clothing_store/models/prefab/trousers", "unique_id": 14, "index": 18, "bbox": [1159, 610, 305, 168], "position": [0.3689999580383301, 0.23014092445373535, 2.189257860183716]}, {"prefab_path": "clothing_store/models/prefab/trousers", "unique_id": 14, "index": 19, "bbox": [1386, 616, 315, 185], "position": [1.128000020980835, 0.2301410436630249, 2.24706768989563]}, {"prefab_path": "clothing_store/models/prefab/sneakers_4", "unique_id": 16, "index": 20, "bbox": [99, 814, 33, 47], "position": [-4.336514949798584, 0.03797274827957153, 2.1530990600585938]}, {"prefab_path": "1514019/Rearranged/Shoes_Preppy", "unique_id": 17, "index": 21, "bbox": [236, 829, 36, 66], "position": [-4.293466567993164, 0.9293829202651978, 2.134406089782715]}, {"prefab_path": "clothing_store/models/prefab/sneakers_4", "unique_id": 16, "index": 22, "bbox": [802, 892, 36, 34], "position": [-1.063675045967102, 0.037972792983055115, 2.1982765197753906]}], "relationships": {"right": {"0": [16, 22, 17], "1": [3, 5, 8], "2": [3, 5, 8], "3": [5, 8, 7], "4": [19, 18, 17], "5": [8, 7, 9], "6": [19], "7": [9, 12], "8": [7, 9, 12], "9": [12], "10": [19], "13": [14, 15, 16], "14": [15, 16, 22], "15": [16, 22, 17], "16": [17, 18, 19], "17": [18, 19], "18": [19], "20": [14, 15, 16], "21": [15, 16, 17], "22": [17, 18, 19]}, "down": {"1": [21, 20, 13], "2": [14, 21, 20], "3": [14, 21, 20], "4": [6], "5": [22, 16, 10], "7": [17, 10, 18], "8": [17, 10, 22], "9": [17, 18, 10], "12": [19, 18, 10], "13": [20], "16": [22, 10], "17": [10], "21": [20, 13], "22": [10]}, "left": {"3": [2, 1], "5": [3, 2, 1], "7": [8, 5, 3], "8": [5, 3, 2], "9": [8, 7, 5], "10": [20, 15, 14], "12": [9, 7, 8], "14": [13, 20], "15": [14, 13, 20], "16": [15, 14, 4], "17": [16, 22, 4], "18": [17, 4, 16], "19": [18, 17, 4], "22": [15, 14, 4]}, "up": {"4": [3, 2, 1], "6": [4, 5, 8], "10": [22, 16, 5], "13": [21, 1, 2], "14": [3, 2, 1], "15": [3, 2, 1], "16": [5, 8, 7], "17": [7, 8, 9], "18": [9, 7, 12], "19": [12], "20": [13, 21, 1], "21": [1, 2, 3], "22": [16, 5, 8]}}}]}