{"scenes": [{"objects": [{"prefab_path": "MensCollection/Prefabs/Rearranged/jacket_2_03", "unique_id": 0, "index": 0, "bbox": [1, 61, 574, 279], "position": [-4.442732810974121, -0.7103862762451172, -1.5217046737670898]}, {"prefab_path": "MensCollection/Prefabs/Rearranged/jacket_1", "unique_id": 1, "index": 1, "bbox": [289, 141, 431, 327], "position": [-1.8300892114639282, -0.45056724548339844, -1.5666561126708984]}, {"prefab_path": "MensCollection/Prefabs/Rearranged/polo shirt 25", "unique_id": 2, "index": 2, "bbox": [641, 228, 280, 182], "position": [-0.998058557510376, 2.385040283203125, -2.8984382152557373]}, {"prefab_path": "MensCollection/Prefabs/Rearranged/jacket_4_09", "unique_id": 3, "index": 3, "bbox": [811, 230, 268, 137], "position": [-0.37658900022506714, 2.3527557849884033, -2.885072708129883]}, {"prefab_path": "MensCollection/Prefabs/Rearranged/jacket_3_02", "unique_id": 4, "index": 4, "bbox": [958, 250, 224, 75], "position": [-5.117886543273926, -2.2526066303253174, -0.8769311904907227]}, {"prefab_path": "1514019/Rearranged/Jean_Jacket", "unique_id": 5, "index": 5, "bbox": [1111, 360, 59, 34], "position": [5.260862350463867, 1.6269629001617432, -0.7172613739967346]}, {"prefab_path": "MensCollection/Prefabs/Rearranged/suit 1", "unique_id": 6, "index": 6, "bbox": [1104, 359, 73, 8], "position": [4.547794342041016, 1.9562866687774658, -0.6450545787811279]}, {"prefab_path": "MensCollection/Prefabs/Rearranged/long_coat_10 1", "unique_id": 7, "index": 7, "bbox": [1213, 313, 83, 45], "position": [5.98333740234375, 1.9023656845092773, -3.8946337699890137]}, {"prefab_path": "MensCollection/Prefabs/Rearranged/jacket_2_06", "unique_id": 8, "index": 8, "bbox": [1259, 315, 79, 50], "position": [7.787705898284912, -1.6074728965759277, 2.043287754058838]}, {"prefab_path": "1208725/Jacket_gray", "unique_id": 9, "index": 9, "bbox": [1303, 322, 76, 61], "position": [6.818510055541992, 0.4889240264892578, -3.527611017227173]}, {"prefab_path": "870230/hoodie09", "unique_id": 10, "index": 10, "bbox": [1365, 324, 75, 54], "position": [6.272047996520996, 2.5024123191833496, -3.5315210819244385]}, {"prefab_path": "870230/hoodie09", "unique_id": 10, "index": 11, "bbox": [1430, 323, 78, 58], "position": [6.272024154663086, 2.5023603439331055, -4.1631879806518555]}, {"prefab_path": "clothing_store/models/prefab/trousers_2", "unique_id": 11, "index": 12, "bbox": [1557, 309, 117, 75], "position": [2.436000108718872, 1.6579999923706055, -5.1020002365112305]}, {"prefab_path": "MensCollection/Prefabs/Rearranged/polo shirt 22", "unique_id": 12, "index": 13, "bbox": [1985, 303, 126, 63], "position": [4.8559112548828125, 2.384760618209839, -7.300678730010986]}, {"prefab_path": "MensCollection/Prefabs/Rearranged/jacket_3_06", "unique_id": 13, "index": 14, "bbox": [1206, 396, 77, 49], "position": [8.58512020111084, -1.2930201292037964, -4.298441410064697]}, {"prefab_path": "MensCollection/Prefabs/Rearranged/long_coat_10 1", "unique_id": 7, "index": 15, "bbox": [1255, 395, 87, 49], "position": [6.032729148864746, 0.8751614093780518, -4.538821220397949]}, {"prefab_path": "MensCollection/Prefabs/Rearranged/shirt_hung_up30", "unique_id": 14, "index": 16, "bbox": [1307, 403, 79, 52], "position": [6.276983261108398, 1.3152124881744385, -2.918836832046509]}, {"prefab_path": "MensCollection/Prefabs/Rearranged/polo shirt 05", "unique_id": 15, "index": 17, "bbox": [1363, 410, 73, 55], "position": [-20.96448516845703, 8.642913818359375, -11.442001342773438]}, {"prefab_path": "1208725/Jacket_gray", "unique_id": 9, "index": 18, "bbox": [1421, 405, 67, 66], "position": [6.975811004638672, -0.42173290252685547, -4.724344253540039]}, {"prefab_path": "clothing_store/models/prefab/cap", "unique_id": 16, "index": 19, "bbox": [1420, 468, 8, 30], "position": [3.013000011444092, 1.5839999914169312, -4.359000205993652]}, {"prefab_path": "MensCollection/Prefabs/Rearranged/long_coat_10", "unique_id": 17, "index": 20, "bbox": [1425, 463, 44, 41], "position": [-0.24582678079605103, 1.6592490673065186, -4.740546703338623]}, {"prefab_path": "MensCollection/Prefabs/Rearranged/jacket_2_03", "unique_id": 0, "index": 21, "bbox": [1473, 439, 32, 15], "position": [-0.6987174153327942, -1.5274724960327148, -6.8358154296875]}, {"prefab_path": "MensCollection/Prefabs/Rearranged/jacket_3_02", "unique_id": 4, "index": 22, "bbox": [1428, 450, 44, 48], "position": [-1.6771858930587769, -3.011418342590332, -10.103826522827148]}, {"prefab_path": "MensCollection/Prefabs/Rearranged/long_coat_10 1", "unique_id": 7, "index": 23, "bbox": [1746, 489, 29, 34], "position": [0.3557920455932617, 1.1852800846099854, -3.0983119010925293]}, {"prefab_path": "1514019/Rearranged/Jeans_Blue_V2", "unique_id": 18, "index": 24, "bbox": [1958, 444, 156, 80], "position": [5.1037092208862305, 1.672162413597107, -7.354883193969727]}, {"prefab_path": "MensCollection/Prefabs/Rearranged/long_coat_06", "unique_id": 19, "index": 25, "bbox": [939, 463, 205, 82], "position": [1.2053241729736328, 0.29413914680480957, -3.4989981651306152]}, {"prefab_path": "clothing_store/models/prefab/trousers", "unique_id": 20, "index": 26, "bbox": [2018, 456, 197, 79], "position": [4.267000198364258, 0.8420000076293945, -7.349999904632568]}, {"prefab_path": "MensCollection/Prefabs/Rearranged/long_coat_10", "unique_id": 17, "index": 27, "bbox": [651, 503, 285, 180], "position": [-0.9966940879821777, 1.4491305351257324, -2.8812901973724365]}, {"prefab_path": "MensCollection/Prefabs/Rearranged/jacket_1", "unique_id": 1, "index": 28, "bbox": [817, 481, 279, 136], "position": [-0.5611811876296997, -1.4698009490966797, -1.6597461700439453]}, {"prefab_path": "MensCollection/Prefabs/Rearranged/long_coat_06", "unique_id": 19, "index": 29, "bbox": [1275, 491, 297, 320], "position": [0.14790749549865723, 0.4459843635559082, -3.839930534362793]}, {"prefab_path": "MensCollection/Prefabs/Rearranged/long_coat_10", "unique_id": 17, "index": 30, "bbox": [344, 550, 238, 291], "position": [-1.6213546991348267, 1.4491305351257324, -2.8815853595733643]}, {"prefab_path": "MensCollection/Prefabs/Rearranged/jacket_2_06", "unique_id": 8, "index": 31, "bbox": [1576, 567, 221, 520], "position": [-2.3755691051483154, -2.324559211730957, -9.492247581481934]}, {"prefab_path": "MensCollection/Prefabs/Rearranged/jacket_2_03", "unique_id": 0, "index": 32, "bbox": [1, 666, 81, 115], "position": [-4.334050178527832, -1.7375907897949219, -1.4603996276855469]}], "relationships": {"down": {"0": [32, 4], "2": [27, 30, 28], "3": [27, 23, 29], "7": [15, 9, 18], "10": [7, 16, 9], "11": [15, 7, 9], "13": [24, 26], "20": [21], "23": [28], "27": [28], "30": [28]}, "right": {"0": [21, 29, 20], "1": [29, 25, 23], "2": [20, 12, 13], "3": [12, 13, 26], "4": [32, 21, 22], "5": [16, 9, 10], "6": [10, 16, 7], "8": [14], "10": [11], "12": [26, 24, 13], "19": [24, 13, 26], "20": [26, 13, 24], "23": [12, 26, 24], "25": [26, 12, 24], "27": [20, 29, 12], "28": [25, 26, 12], "29": [26, 12, 24], "30": [20, 29, 12], "32": [21, 29, 31]}, "up": {"32": [0], "1": [2, 3], "4": [0], "7": [11, 10], "9": [10, 11, 7], "14": [11, 10], "15": [11, 7, 10], "16": [10], "18": [11, 7, 10], "21": [20], "23": [3], "24": [13], "26": [13], "27": [2, 3], "28": [3, 27, 2], "29": [3], "30": [2]}, "left": {"7": [6, 5], "9": [5, 6], "10": [6, 5], "11": [10, 6, 5], "12": [23, 3, 25], "13": [19, 12, 3], "14": [5, 8, 6], "15": [6, 5, 28], "16": [5, 6], "18": [5, 6, 28], "19": [23, 3, 27], "20": [30, 27, 2], "21": [32, 4, 0], "22": [4, 32, 0], "23": [1], "24": [19, 12, 23], "25": [1, 28, 0], "26": [25, 23, 12], "29": [1, 27, 30], "31": [4, 32, 0], "32": [4]}}}]}