{"Items":[{"name":"AreaRug_MROW8373_v6_LOD2 (1)(Clone)","prefabPath":"modified_wayfair_assets/AreaRug/AreaRug_MROW8373_v6_LOD2 (1)","bbox":[377,578,210,1059],"position":[-585.0,0.10000000149011612,-1040.0]},{"name":"CouchChair_VKGL1857_v6_LOD2 (2)(Clone)","prefabPath":"modified_wayfair_assets/CouchChair/CouchChair_VKGL1857_v6_LOD2 (2)","bbox":[353,493,148,136],"position":[-793.0,0.00006103515625,-909.0]},{"name":"CouchChair_GRYL4160(Clone)","prefabPath":"modified_wayfair_assets/CouchChair/CouchChair_GRYL4160","bbox":[488,524,53,66],"position":[-770.052490234375,0.00006103515625,-773.2368774414063]},{"name":"EndTable_ATGR2663_v6_LOD2 (1)(Clone)","prefabPath":"modified_wayfair_assets/EndTable/EndTable_ATGR2663_v6_LOD2 (1)","bbox":[292,570,164,116],"position":[-794.615234375,-0.0001220703125,-1028.5499267578125]},{"name":"Lamp_CHLH3796(Clone)","prefabPath":"modified_wayfair_assets/Lamp/Lamp_CHLH3796","bbox":[296,408,304,156],"position":[-789.0,64.0,-1017.7999877929688]},{"name":"Couch_TRPT1526_v6_LOD2(Clone)","prefabPath":"modified_wayfair_assets/Sofa/Couch_TRPT1526_v6_LOD2","bbox":[938,515,66,78],"position":[-400.0,0.000030517578125,-867.0]},{"name":"CouchChair_ALTL2260(Clone)","prefabPath":"modified_wayfair_assets/CouchChair/CouchChair_ALTL2260","bbox":[694,471,98,223],"position":[-519.5999755859375,36.0,-791.7000122070313]},{"name":"AreaRug_MCRR7867_v6_LOD2(Clone)","prefabPath":"modified_wayfair_assets/AreaRug/AreaRug_MCRR7867_v6_LOD2","bbox":[765,440,33,201],"position":[-179.1999969482422,0.10000000149011612,0.0]},{"name":"Table_LRKM2887_v6_LOD2(Clone)","prefabPath":"modified_wayfair_assets/Table/Table_LRKM2887_v6_LOD2","bbox":[795,413,39,85],"position":[-182.6999969482422,0.0,104.12525939941406]},{"name":"Chair_CSTD2801_v6_LOD2 (1)(Clone)","prefabPath":"modified_wayfair_assets/Chair/Chair_CSTD2801_v6_LOD2 (1)","bbox":[840,406,41,33],"position":[-182.901611328125,21.473678588867189,-39.423797607421878]},{"name":"AreaRug_BNGL9021_v6_LOD2(Clone)","prefabPath":"modified_wayfair_assets/AreaRug/AreaRug_BNGL9021_v6_LOD2","bbox":[509,435,18,274],"position":[-624.0,0.10000000149011612,349.0]},{"name":"Sofa_WADL4451_v6_LOD2(Clone)","prefabPath":"modified_wayfair_assets/Sofa/Sofa_WADL4451_v6_LOD2","bbox":[590,405,30,75],"position":[-623.0,0.0,564.9000244140625]},{"name":"EndTable_ATGR2663_v6_LOD2(Clone)","prefabPath":"modified_wayfair_assets/EndTable/EndTable_ATGR2663_v6_LOD2","bbox":[571,423,7,21],"position":[-738.3855590820313,-0.00006103515625,173.13839721679688]},{"name":"EndTable_ATGR2663_v6_LOD2 1(Clone)","prefabPath":"modified_wayfair_assets/EndTable/EndTable_ATGR2663_v6_LOD2 1","bbox":[578,416,14,16],"position":[-738.3855590820313,-0.00006103515625,512.0]},{"name":"CoffeeTable_BLET2606(Clone)","prefabPath":"modified_wayfair_assets/CoffeeTable/CoffeeTable_BLET2606","bbox":[628,426,6,29],"position":[-592.6104736328125,0.000030517578125,266.8133239746094]},{"name":"CoffeeTable_BLET2606(Clone)","prefabPath":"modified_wayfair_assets/CoffeeTable/CoffeeTable_BLET2606","bbox":[617,422,5,30],"position":[-598.0,0.000030517578125,460.0]},{"name":"Lamp_CHLH3796(Clone)","prefabPath":"modified_wayfair_assets/Lamp/Lamp_CHLH3796","bbox":[531,420,23,16],"position":[-804.4570922851563,0.0,78.14657592773438]},{"name":"AreaRug_MCRR7867_v6_LOD2(Clone)","prefabPath":"modified_wayfair_assets/AreaRug/AreaRug_MCRR7867_v6_LOD2","bbox":[525,464,91,218],"position":[-617.0,1.0,-446.0]},{"name":"Lamp_HES3357(Clone)","prefabPath":"modified_wayfair_assets/Lamp/Lamp_HES3357","bbox":[545,439,47,19],"position":[-756.5,0.0000152587890625,-358.20001220703127]},{"name":"camera","prefabPath":"camera","bbox":[-1,-1,-1,-1],"position":[-683.853759765625,150.0,-1357.158447265625]},{"name":"camera_right","prefabPath":"camera","bbox":[-1,-1,-1,-1],"position":[0.9816271662712097,-1.1641532182693482e-10,-0.1908089816570282]},{"name":"camera_forward","prefabPath":"camera","bbox":[-1,-1,-1,-1],"position":[0.1907799243927002,-0.017452405765652658,0.981477677822113]},{"name":"camera_up","prefabPath":"camera","bbox":[-1,-1,-1,-1],"position":[0.003330076113343239,0.9998477101325989,0.017131755128502847]}]}