{"players": {"GM": "Game master for GenInsta", "Player 1": "Player A: anyscale-llama-3-8b-instruct-hf", "Player 2": "Player B: ObjectID Evaluator (Programmatic)"}, "turns": [[], [{"from": "GM", "to": "Player 1", "timestamp": "2024-04-26T14:55:04.983608", "action": {"type": "send message", "content": "You are a helpful assistant tasked with identifying specific object IDs from references made in conversation snippets.\n\nThe scene contains multiple objects, each identified by an ID and characterized by attributes including name, color, and size. Analyze the conversation to determine which objects are being mentioned based on their described attributes. Match these details with the attributes of objects in the scene to accurately identify and return the corresponding object IDs. If a conversation refers to multiple objects, detect and respond with all relevant object IDs. Ensure that you do not repeat the previously detected ObjectID list again for the current conversation.\n\nBelow is the scene description. Each line contains a tuple with the format (object_id, type, color, size), describing each object in the scene.\n\nobject_id, object_type, object_color, object_size\n5, hoodie, brown, XXL\n21, hoodie, brown, XXL\n7, hoodie, brown, XXL\n29, hoodie, brown, XXL\n19, hat, grey, S\n\n\nYour response should list the matched object IDs under the label 'ObjectID', followed by a newline.\n\nDo not generate any other text or explanations.\n\nLet's begin\nUser: Hello, I'm looking for a hoodie with good reviews and full-length sleeves.\nSystem: Sure!  Over to the bottom right you can see a brown one on the circular rack.  At the back wall in the section to the left of the bright blue jacket you can see a couple more brown hoodies.\n"}}, {"from": "Player 1", "to": "GM", "timestamp": "2024-04-26T14:55:06.117637", "action": {"type": "get message", "content": "ObjectID\n5\n21\n7"}}, {"from": "GM", "to": "GM", "timestamp": "2024-04-26T14:55:06.118156", "action": {"type": "metadata", "content": {"prediction": [5, 21, 7], "groundtruth": [5, 21, 7]}}}, {"from": "GM", "to": "GM", "timestamp": "2024-04-26T14:55:06.118293", "action": {"type": "parse", "content": "answer confirms to rules"}}], [{"from": "GM", "to": "Player 1", "timestamp": "2024-04-26T14:55:06.118482", "action": {"type": "send message", "content": "User: Anything else with good reviews?\nSystem: Yea, there's actually one more brown hoodie on the round rack at the front right.\n"}}, {"from": "Player 1", "to": "GM", "timestamp": "2024-04-26T14:55:07.672068", "action": {"type": "get message", "content": "ObjectID\n5\n21\n7"}}, {"from": "GM", "to": "GM", "timestamp": "2024-04-26T14:55:07.672609", "action": {"type": "metadata", "content": {"prediction": [5, 21, 7], "groundtruth": [29]}}}, {"from": "GM", "to": "GM", "timestamp": "2024-04-26T14:55:07.672758", "action": {"type": "parse", "content": "answer confirms to rules"}}], [{"from": "GM", "to": "Player 1", "timestamp": "2024-04-26T14:55:07.672908", "action": {"type": "send message", "content": "User: Anything similar to that one in size but in a black color?\nSystem: Sorry, I don't have anything else like that right now.\nUser: Can you compare the sizes and ratings of the brown hoodie at the front right with the righthand one of the two hanging at the back.\nSystem: Sure, they're actually both XXL and rated at 4.0.\n"}}, {"from": "Player 1", "to": "GM", "timestamp": "2024-04-26T14:55:08.788829", "action": {"type": "get message", "content": "ObjectID\n5\n21\n7\n29"}}, {"from": "GM", "to": "GM", "timestamp": "2024-04-26T14:55:08.789370", "action": {"type": "metadata", "content": {"prediction": [5, 21, 7, 29], "groundtruth": [21, 7]}}}, {"from": "GM", "to": "GM", "timestamp": "2024-04-26T14:55:08.789515", "action": {"type": "parse", "content": "answer confirms to rules"}}], [{"from": "GM", "to": "Player 1", "timestamp": "2024-04-26T14:55:08.789670", "action": {"type": "send message", "content": "User: Ok thanks.  Well I really like this grey hat beside the camo one, can you put it in my cart?\nSystem: Sure, the grey hat is now in your cart.\n"}}, {"from": "Player 1", "to": "GM", "timestamp": "2024-04-26T14:55:09.633247", "action": {"type": "get message", "content": "ObjectID\n5\n21\n7\n29"}}, {"from": "GM", "to": "GM", "timestamp": "2024-04-26T14:55:09.633719", "action": {"type": "metadata", "content": {"prediction": [5, 21, 7, 29], "groundtruth": [19]}}}, {"from": "GM", "to": "GM", "timestamp": "2024-04-26T14:55:09.633791", "action": {"type": "parse", "content": "answer confirms to rules"}}, {"from": "GM", "to": "GM", "timestamp": "2024-04-26T14:55:09.633841", "action": {"type": "info", "content": "game successful"}}, {"from": "GM", "to": "GM", "timestamp": "2024-04-26T14:55:09.633894", "action": {"type": "info", "content": "end game"}}]], "n_turns": 4, "Played turns": 4, "Complete turns": 4, "Aborted": false, "Lose": false, "Request Count": [0, 1, 1, 1, 1], "Parsed Request Count": [0, 1, 1, 1, 1], "Violated Request Count": [0, 0, 0, 0, 0], "Evaluation": {"1": {"groundtruth": [5, 21, 7], "prediction": [5, 21, 7]}, "2": {"groundtruth": [29], "prediction": [5, 21, 7]}, "3": {"groundtruth": [21, 7], "prediction": [5, 21, 7, 29]}, "4": {"groundtruth": [19], "prediction": [5, 21, 7, 29]}}}