{"players": {"GM": "Game master for GenInsta", "Player 1": "Player A: anyscale-llama-3-8b-instruct-hf", "Player 2": "Player B: ObjectID Evaluator (Programmatic)"}, "turns": [[], [{"from": "GM", "to": "Player 1", "timestamp": "2024-04-30T17:54:31.350856", "action": {"type": "send message", "content": "You are a helpful assistant tasked with identifying specific object IDs from references made in conversation snippets.\n\nThe scene contains multiple objects, each identified by an ID and characterized by attributes including name, color, and size. Analyze the conversation to determine which objects are being mentioned based on their described attributes. Match these details with the attributes of objects in the scene to accurately identify and return the corresponding object IDs. If a conversation refers to multiple objects, detect and respond with all relevant object IDs. Ensure that you do not repeat the previously detected ObjectID list again for the current conversation.\n\nBelow is the scene description. Each line contains a tuple with the format (object_id, type, color, size), describing each object in the scene.\n\nobject_id, object_type, object_color, object_size\n14, jacket, grey, XS\n19, jacket, grey, XS\n11, jacket, blue, S\n9, jacket, grey, M\n4, jacket, red, white, XS\n\n\nYour response should list the matched object IDs under the label 'ObjectID', followed by a newline.\n\nDo not generate any other text or explanations.\n\nLet's begin\nUser: Hi there. Is there a jacket with full-length sleeves?\nSystem: I found a grey one in the back left, a grey one in the front right, and a blue one on the top right in front of us.\n"}}, {"from": "Player 1", "to": "GM", "timestamp": "2024-04-30T17:54:32.895766", "action": {"type": "get message", "content": "ObjectID\n9, 14, 19"}}, {"from": "GM", "to": "GM", "timestamp": "2024-04-30T17:54:32.896371", "action": {"type": "metadata", "content": {"prediction": [9, 14, 19], "groundtruth": [14, 19, 11]}}}], [{"from": "GM", "to": "Player 1", "timestamp": "2024-04-30T17:54:32.896548", "action": {"type": "send message", "content": "User: Could you compare the two grey ones?\nSystem: Both ones on display are XS, and both are only available in XS.\n"}}, {"from": "Player 1", "to": "GM", "timestamp": "2024-04-30T17:54:34.042226", "action": {"type": "get message", "content": "ObjectID\n14\n19"}}, {"from": "GM", "to": "GM", "timestamp": "2024-04-30T17:54:34.042731", "action": {"type": "metadata", "content": {"prediction": [14, 19], "groundtruth": [14, 19]}}}], [{"from": "GM", "to": "Player 1", "timestamp": "2024-04-30T17:54:34.042913", "action": {"type": "send message", "content": "User: Is there a jacket you'd recommend?\nSystem: Besides the grey one in the bottom left, there's another grey one on the table, and a red and white one in the top row in the back left corner.\n"}}, {"from": "Player 1", "to": "GM", "timestamp": "2024-04-30T17:54:35.064444", "action": {"type": "get message", "content": "ObjectID\n14\n19"}}, {"from": "GM", "to": "GM", "timestamp": "2024-04-30T17:54:35.064942", "action": {"type": "metadata", "content": {"prediction": [14, 19], "groundtruth": [14, 9, 4]}}}, {"from": "GM", "to": "GM", "timestamp": "2024-04-30T17:54:35.065091", "action": {"type": "info", "content": "dialogue completed"}}, {"from": "GM", "to": "GM", "timestamp": "2024-04-30T17:54:35.065214", "action": {"type": "info", "content": "end game"}}]], "n_turns": 3, "Played turns": 3, "Complete turns": 3, "Aborted": false, "Lose": false, "Request Count": [0, 1, 1, 1], "Parsed Request Count": [0, 1, 1, 1], "Violated Request Count": [0, 0, 0, 0], "Evaluation": {"1": {"groundtruth": [14, 19, 11], "prediction": [9, 14, 19]}, "2": {"groundtruth": [14, 19], "prediction": [14, 19]}, "3": {"groundtruth": [14, 9, 4], "prediction": [14, 19]}}, "Dialogue": {"use_dialogue_context": true, "total_dialogues": [{"uapairs": [["User: Hi there. Is there a jacket with full-length sleeves?", "System: I found a grey one in the back left, a grey one in the front right, and a blue one on the top right in front of us."]], "scene_ids": {"0": "cloth_store_3_7_0"}, "disambiguation_label": 0, "groundtruth": [14, 19, 11], "details": {"14": {"prefab_path": "MensCollection/Prefabs/Rearranged/jacket_4_05", "unique_id": 8, "index": 14, "bbox": [517, 398, 150, 93], "position": [-3.9438319206237793, 1.6498987674713135, -10.297155380249023]}, "19": {"prefab_path": "MensCollection/Prefabs/Rearranged/jacket_4_05", "unique_id": 8, "index": 19, "bbox": [1254, 525, 263, 136], "position": [-4.673531532287598, 1.7557804584503174, -2.8122317790985107]}, "11": {"prefab_path": "MensCollection/Prefabs/Rearranged/jacket_3_06", "unique_id": 0, "index": 11, "bbox": [1397, 1, 788, 700], "position": [2.238577365875244, -0.33806705474853516, -0.7498946189880371]}}}, {"uapairs": [["User: Could you compare the two grey ones?", "System: Both ones on display are XS, and both are only available in XS."]], "scene_ids": {"0": "cloth_store_3_7_0"}, "disambiguation_label": 0, "groundtruth": [14, 19], "details": {"14": {"prefab_path": "MensCollection/Prefabs/Rearranged/jacket_4_05", "unique_id": 8, "index": 14, "bbox": [517, 398, 150, 93], "position": [-3.9438319206237793, 1.6498987674713135, -10.297155380249023]}, "19": {"prefab_path": "MensCollection/Prefabs/Rearranged/jacket_4_05", "unique_id": 8, "index": 19, "bbox": [1254, 525, 263, 136], "position": [-4.673531532287598, 1.7557804584503174, -2.8122317790985107]}}}, {"uapairs": [["User: Is there a jacket you'd recommend?", "System: Besides the grey one in the bottom left, there's another grey one on the table, and a red and white one in the top row in the back left corner."]], "scene_ids": {"0": "cloth_store_3_7_0"}, "disambiguation_label": 0, "groundtruth": [14, 9, 4], "details": {"14": {"prefab_path": "MensCollection/Prefabs/Rearranged/jacket_4_05", "unique_id": 8, "index": 14, "bbox": [517, 398, 150, 93], "position": [-3.9438319206237793, 1.6498987674713135, -10.297155380249023]}, "9": {"prefab_path": "1514019/Rearranged/Jacket_Grey", "unique_id": 5, "index": 9, "bbox": [943, 306, 146, 63], "position": [-4.293859958648682, 1.507941722869873, -4.800738334655762]}, "4": {"prefab_path": "1208725/Jacket_red", "unique_id": 3, "index": 4, "bbox": [617, 266, 122, 63], "position": [-6.131339073181152, 3.3139808177948, -6.461416244506836]}}}], "disambiguation_label": 0}}