{"players": {"GM": "Game master for GenInsta", "Player 1": "Player A: anyscale-llama-3-8b-instruct-hf", "Player 2": "Player B: ObjectID Evaluator (Programmatic)"}, "turns": [[], [{"from": "GM", "to": "Player 1", "timestamp": "2024-04-26T13:23:17.869368", "action": {"type": "send message", "content": "You are a helpful assistant tasked with identifying specific object IDs from references made in conversation snippets.\n\nThe scene contains multiple objects, each identified by an ID and characterized by attributes including name, color, and size. Analyze the conversation to determine which objects are being mentioned based on their described attributes. Match these details with the attributes of objects in the scene to accurately identify and return the corresponding object IDs. If a conversation refers to multiple objects, detect and respond with all relevant object IDs. Ensure that you do not repeat the previously detected ObjectID list again for the current conversation.\n\nBelow is the scene description. Each line contains a tuple with the format (object_id, type, color, size), describing each object in the scene.\n\nobject_id, object_type, object_color, object_size\n38, joggers, dark green, XL\n2, hoodie, blue, S\n22, hoodie, green, S\n73, hoodie, blue, S\n33, coat, grey, XXL\n\n\nYour response should list the matched object IDs under the label 'ObjectID', followed by a newline.\n\nDo not generate any other text or explanations.\n\nLet's begin\nUser: Can you show me some joggers? I want some that will go well with my wardrobe.\nSystem: What do you think of the dark green joggers on the right wall?\n"}}, {"from": "Player 1", "to": "GM", "timestamp": "2024-04-26T13:23:18.685503", "action": {"type": "get message", "content": "ObjectID\n38"}}, {"from": "GM", "to": "GM", "timestamp": "2024-04-26T13:23:18.686355", "action": {"type": "metadata", "content": {"prediction": [38], "groundtruth": [38]}}}, {"from": "GM", "to": "GM", "timestamp": "2024-04-26T13:23:18.686530", "action": {"type": "parse", "content": "answer confirms to rules"}}], [{"from": "GM", "to": "Player 1", "timestamp": "2024-04-26T13:23:18.686684", "action": {"type": "send message", "content": "User: Great, now show me some hoodies that will go well with that.\nSystem: There are two blue hoodies and a green hoodie which you might like.\n"}}, {"from": "Player 1", "to": "GM", "timestamp": "2024-04-26T13:23:19.702618", "action": {"type": "get message", "content": "ObjectID\n38"}}, {"from": "GM", "to": "GM", "timestamp": "2024-04-26T13:23:19.703405", "action": {"type": "metadata", "content": {"prediction": [38], "groundtruth": [2, 22, 73]}}}, {"from": "GM", "to": "GM", "timestamp": "2024-04-26T13:23:19.703575", "action": {"type": "parse", "content": "answer confirms to rules"}}], [{"from": "GM", "to": "Player 1", "timestamp": "2024-04-26T13:23:19.703723", "action": {"type": "send message", "content": "User: Actually, now I want you to show me something that has the same size and price range as the black t-shirt but from Global Voyager and with a long sleeve length.\nSystem: Sorry, nothing matches your description. What else may I help you with?\nUser: Add the green hoodie to my cart.\nSystem: Okay, I will add that item to your cart.\n"}}, {"from": "Player 1", "to": "GM", "timestamp": "2024-04-26T13:23:20.446563", "action": {"type": "get message", "content": "ObjectID\n38"}}, {"from": "GM", "to": "GM", "timestamp": "2024-04-26T13:23:20.447008", "action": {"type": "metadata", "content": {"prediction": [38], "groundtruth": [22]}}}, {"from": "GM", "to": "GM", "timestamp": "2024-04-26T13:23:20.447127", "action": {"type": "parse", "content": "answer confirms to rules"}}], [{"from": "GM", "to": "Player 1", "timestamp": "2024-04-26T13:23:20.447308", "action": {"type": "send message", "content": "User: Also add the grey coat.\nSystem: Okay, that item will also be added to your cart.\n"}}, {"from": "Player 1", "to": "GM", "timestamp": "2024-04-26T13:23:21.897565", "action": {"type": "get message", "content": "ObjectID\n38"}}, {"from": "GM", "to": "GM", "timestamp": "2024-04-26T13:23:21.898178", "action": {"type": "metadata", "content": {"prediction": [38], "groundtruth": [33]}}}, {"from": "GM", "to": "GM", "timestamp": "2024-04-26T13:23:21.898326", "action": {"type": "parse", "content": "answer confirms to rules"}}, {"from": "GM", "to": "GM", "timestamp": "2024-04-26T13:23:21.898469", "action": {"type": "info", "content": "game successful"}}, {"from": "GM", "to": "GM", "timestamp": "2024-04-26T13:23:21.898589", "action": {"type": "info", "content": "end game"}}]], "n_turns": 4, "Played turns": 4, "Complete turns": 4, "Aborted": false, "Lose": false, "Request Count": [0, 1, 1, 1, 1], "Parsed Request Count": [0, 1, 1, 1, 1], "Violated Request Count": [0, 0, 0, 0, 0], "Evaluation": {"1": {"groundtruth": [38], "prediction": [38]}, "2": {"groundtruth": [2, 22, 73], "prediction": [38]}, "3": {"groundtruth": [22], "prediction": [38]}, "4": {"groundtruth": [33], "prediction": [38]}}}