{"players": {"GM": "Game master for GenInsta", "Player 1": "Player A: anyscale-llama-3-8b-instruct-hf", "Player 2": "Player B: ObjectID Evaluator (Programmatic)"}, "turns": [[], [{"from": "GM", "to": "Player 1", "timestamp": "2024-04-26T14:42:24.918078", "action": {"type": "send message", "content": "You are a helpful assistant tasked with identifying specific object IDs from references made in conversation snippets.\n\nThe scene contains multiple objects, each identified by an ID and characterized by attributes including name, color, and size. Analyze the conversation to determine which objects are being mentioned based on their described attributes. Match these details with the attributes of objects in the scene to accurately identify and return the corresponding object IDs. If a conversation refers to multiple objects, detect and respond with all relevant object IDs. Ensure that you do not repeat the previously detected ObjectID list again for the current conversation.\n\nBelow is the scene description. Each line contains a tuple with the format (object_id, type, color, size), describing each object in the scene.\n\nobject_id, object_type, object_color, object_size\n0, Bed, grey, NA\n4, Bed, grey, NA\n5, AreaRug, white, NA\n\n\nYour response should list the matched object IDs under the label 'ObjectID', followed by a newline.\n\nDo not generate any other text or explanations.\n\nLet's begin\nUser: I'm shopping for a new bed to match my mission style end tables. Do you have a suggestion?\nSystem: Either the grey bed in front of you or the grey bed to the right may be of interest.\n"}}, {"from": "Player 1", "to": "GM", "timestamp": "2024-04-26T14:42:26.445540", "action": {"type": "get message", "content": "ObjectID\n0\n4"}}, {"from": "GM", "to": "GM", "timestamp": "2024-04-26T14:42:26.446264", "action": {"type": "metadata", "content": {"prediction": [0, 4], "groundtruth": [0, 4]}}}, {"from": "GM", "to": "GM", "timestamp": "2024-04-26T14:42:26.446398", "action": {"type": "parse", "content": "answer confirms to rules"}}], [{"from": "GM", "to": "Player 1", "timestamp": "2024-04-26T14:42:26.446526", "action": {"type": "send message", "content": "User: Can you find something that is similar in price to the grey one straight ahead of us, but white instead of grey?\nSystem: We don't carry anything like that.\nUser: How about that Uptown Studio rug I saw last time I shopped with you?\nSystem: The white rug on the left is by Uptown Studio.\n"}}, {"from": "Player 1", "to": "GM", "timestamp": "2024-04-26T14:42:27.909037", "action": {"type": "get message", "content": "ObjectID\n0\n4"}}, {"from": "GM", "to": "GM", "timestamp": "2024-04-26T14:42:27.909575", "action": {"type": "metadata", "content": {"prediction": [0, 4], "groundtruth": [5]}}}, {"from": "GM", "to": "GM", "timestamp": "2024-04-26T14:42:27.909711", "action": {"type": "parse", "content": "answer confirms to rules"}}], [{"from": "GM", "to": "Player 1", "timestamp": "2024-04-26T14:42:27.909852", "action": {"type": "send message", "content": "User: Yes, that is the one. Add it!\nSystem: Sure, I've updated your cart to reflect the white Uptown Studio rug.\n"}}, {"from": "Player 1", "to": "GM", "timestamp": "2024-04-26T14:42:29.401735", "action": {"type": "get message", "content": "ObjectID\n0\n4\n5"}}, {"from": "GM", "to": "GM", "timestamp": "2024-04-26T14:42:29.402329", "action": {"type": "metadata", "content": {"prediction": [0, 4, 5], "groundtruth": [5]}}}, {"from": "GM", "to": "GM", "timestamp": "2024-04-26T14:42:29.402467", "action": {"type": "parse", "content": "answer confirms to rules"}}, {"from": "GM", "to": "GM", "timestamp": "2024-04-26T14:42:29.402614", "action": {"type": "info", "content": "game successful"}}, {"from": "GM", "to": "GM", "timestamp": "2024-04-26T14:42:29.402744", "action": {"type": "info", "content": "end game"}}]], "n_turns": 3, "Played turns": 3, "Complete turns": 3, "Aborted": false, "Lose": false, "Request Count": [0, 1, 1, 1], "Parsed Request Count": [0, 1, 1, 1], "Violated Request Count": [0, 0, 0, 0], "Evaluation": {"1": {"groundtruth": [0, 4], "prediction": [0, 4]}, "2": {"groundtruth": [5], "prediction": [0, 4]}, "3": {"groundtruth": [5], "prediction": [0, 4, 5]}}}